foo_parameterization/__init__.py
foo_parameterization/foo_parameterization.py
tests/__init__.py
tests/test_foo_parameterization.py
foo_parameterization_vandit-0.1.0.dist-info/METADATA
foo_parameterization_vandit-0.1.0.dist-info/WHEEL
foo_parameterization_vandit-0.1.0.dist-info/top_level.txt
foo_parameterization_vandit-0.1.0.dist-info/RECORD
