Metadata-Version: 2.1
Name: foo_parameterization_vandit
Version: 0.1.0
Summary: Package to calculate the Foo et al. parameterization for a sphere.
Home-page: https://github.com/vandit1920/foo_parametrization
Author: Vandit Jain
Author-email: Vandit Jain <vanditjain19@gmail.com>
Project-URL: Homepage, https://github.com/vandit1920/foo_parameterization
Classifier: Programming Language :: Python :: 3
Classifier: License :: OSI Approved :: MIT License
Classifier: Operating System :: OS Independent
Requires-Python: >=3.6
